famie/__init__.py
famie/constants.py
famie/api/__init__.py
famie/api/active_learning/__init__.py
famie/api/active_learning/config.py
famie/api/active_learning/constants.py
famie/api/active_learning/controllers.py
famie/api/active_learning/models.py
famie/api/active_learning/trainers.py
famie/api/active_learning/utils.py
famie/api/api_fns/__init__.py
famie/api/api_fns/utils.py
famie/api/api_fns/project_creation/__init__.py
famie/api/api_fns/project_creation/common.py
famie/api/api_fns/project_creation/supervised.py
famie/api/api_fns/project_settings/__init__.py
famie/api/api_fns/project_settings/supervised.py
famie/api/blueprints/__init__.py
famie/api/blueprints/common.py
famie/api/blueprints/supervised.py
famie/api/static/bundle.js
famie/api/templates/index.html
famie/config/__init__.py
famie/config/common_config.ini
famie/config/config_reader.py
famie/entry_points/__init__.py
famie/entry_points/run_app.py
famie/scripts/__init__.py
famie/scripts/start_app.py
famie/scripts/uninstall_app.py
famie-0.3.0.data/data/requirements.txt
famie-0.3.0.dist-info/LICENSE
famie-0.3.0.dist-info/METADATA
famie-0.3.0.dist-info/WHEEL
famie-0.3.0.dist-info/entry_points.txt
famie-0.3.0.dist-info/top_level.txt
famie-0.3.0.dist-info/RECORD
